beekeeper/readers/ibm_cos/__init__.py
beekeeper/readers/ibm_cos/base.py
beekeeper_readers_ibm_cos-1.0.0.dist-info/METADATA
beekeeper_readers_ibm_cos-1.0.0.dist-info/WHEEL
beekeeper_readers_ibm_cos-1.0.0.dist-info/RECORD
